marshmallow_jsonapi/__init__.py
marshmallow_jsonapi/exceptions.py
marshmallow_jsonapi/fields.py
marshmallow_jsonapi/flask.py
marshmallow_jsonapi/schema.py
marshmallow_jsonapi/utils.py
marshmallow_jsonapi-0.23.2.dist-info/LICENSE
marshmallow_jsonapi-0.23.2.dist-info/METADATA
marshmallow_jsonapi-0.23.2.dist-info/WHEEL
marshmallow_jsonapi-0.23.2.dist-info/top_level.txt
marshmallow_jsonapi-0.23.2.dist-info/RECORD
