Metadata-Version: 2.1
Name: marshmallow-jsonapi
Version: 0.23.2
Summary: JSON API 1.0 (https://jsonapi.org) formatting with marshmallow
Home-page: https://github.com/marshmallow-code/marshmallow-jsonapi
Author: Steven Loria
Author-email: sloria1@gmail.com
License: MIT
Project-URL: Bug Reports, https://github.com/marshmallow-code/marshmallow-jsonapi/issues
Project-URL: Funding, https://opencollective.com/marshmallow
Keywords: marshmallow-jsonapi marshmallow marshalling serialization jsonapi deserialization validation
Platform: UNKNOWN
Classifier: Intended Audience :: Developers
Classifier: License :: OSI Approved :: MIT License
Classifier: Natural Language :: English
Classifier: Programming Language :: Python :: 3
Classifier: Programming Language :: Python :: 3.6
Classifier: Programming Language :: Python :: 3.7
Requires-Python: >=3.6
Provides-Extra: tests
Provides-Extra: lint
Provides-Extra: dev
